sit/__init__.py
sit/__init__.pyi
sit/configfile.py
sit/configfile.pyi
sit/exceptions.py
sit/exceptions.pyi
sit/files.py
sit/files.pyi
sit/libmgmt.py
sit/libmgmt.pyi
sit/render.py
sit/render.pyi
sit/cpp/CMakeLists.txt
sit/cpp/cmake/SITConfig.cmake.in
sit/cpp/libsit/bufwidth.hpp
sit/cpp/libsit/linkwrap.hpp
sit/cpp/libsit/sit.hpp
sit/cpp/libsit/sitbuf.hpp
sit/cpp/libsit/socket.hpp
sit/cpp/libsit/zmq.hpp
sit/hdl/__init__.py
sit/hdl/__init__.pyi
sit/hdl/pyrtl/__init__.py
sit/hdl/pyrtl/__init__.pyi
sit/hdl/pyrtl/__pycache__/__init__.cpython-310.pyc
sit/hdl/pyrtl/templates/driver
sit/hdl/systemc/__init__.py
sit/hdl/systemc/__init__.pyi
sit/hdl/systemc/__pycache__/__init__.cpython-310.pyc
sit/hdl/systemc/templates/driver
sit/hdl/templates/comp
sit/hdl/verilog/__init__.py
sit/hdl/verilog/__init__.pyi
sit/hdl/verilog/__pycache__/__init__.cpython-310.pyc
sit/hdl/verilog/templates/Makefile.config
sit/hdl/verilog/templates/driver
sst_it-1.1.0.dist-info/LICENSE
sst_it-1.1.0.dist-info/METADATA
sst_it-1.1.0.dist-info/WHEEL
sst_it-1.1.0.dist-info/entry_points.txt
sst_it-1.1.0.dist-info/top_level.txt
sst_it-1.1.0.dist-info/RECORD
