Metadata-Version: 2.1
Name: sst_it
Version: 1.1.0
Summary: SST Interoperability Toolkit
Author-email: lpsmodsim <modsim@lps.umd.edu>
License: Copyright 2023 lpsmodsimteam
Project-URL: Homepage, https://github.com/lpsmodsimteam/SIT
Classifier: Programming Language :: Python :: 3
Classifier: License :: OSI Approved :: MIT License
Classifier: Operating System :: OS Independent
Requires-Python: >=3.6
License-File: LICENSE
